streamlit_data_profile_viewer/__init__.py
streamlit_data_profile_viewer-0.1.2.dist-info/LICENSE
streamlit_data_profile_viewer-0.1.2.dist-info/METADATA
streamlit_data_profile_viewer-0.1.2.dist-info/WHEEL
streamlit_data_profile_viewer-0.1.2.dist-info/top_level.txt
streamlit_data_profile_viewer-0.1.2.dist-info/RECORD
