Metadata-Version: 2.1
Name: streamlit-data-profile-viewer
Version: 0.1.2
Summary: Data profile viewer component for Streamlit
Home-page: UNKNOWN
Author: Sonia Castelo Quispe
Author-email: 
License: UNKNOWN
Platform: UNKNOWN
Requires-Python: >=3.6
Requires-Dist: streamlit (>=0.63)
Requires-Dist: data-profile-viewer (>=0.2.6)
